astrokundali/__init__.py
astrokundali/__main__.py
astrokundali/ashtakvarga.py
astrokundali/astakvarga.py
astrokundali/astro_chart.py
astrokundali/astro_data.py
astrokundali/birthtime_finder.py
astrokundali/dasha.py
astrokundali/date_converter.py
astrokundali/dispositions.py
astrokundali/horoscope.py
astrokundali/houses.py
astrokundali/marriage_timing.py
astrokundali/match.py
astrokundali/plotter.py
astrokundali/yogas_detector.py
astrokundali/data/arudha_lagna.json
astrokundali/data/ascendant_interpretations.json
astrokundali/data/aspects_interpretations.json
astrokundali/data/conj_interpretations.json
astrokundali/data/cons_rem_marriage.json
astrokundali/data/elements.json
astrokundali/data/general_interpretations.json
astrokundali/data/rashi_descriptions.json
astrokundali/data/yogas.json
astrokundali-0.3.0.dist-info/licenses/LICENSE
astrokundali-0.3.0.dist-info/METADATA
astrokundali-0.3.0.dist-info/WHEEL
astrokundali-0.3.0.dist-info/entry_points.txt
astrokundali-0.3.0.dist-info/top_level.txt
astrokundali-0.3.0.dist-info/RECORD
