Metadata-Version: 2.4
Name: astrokundali
Version: 0.3.0
Summary: Generate and plot North-Indian Lagna Kundali charts using pyswisseph. Flexible astrokundali package with Different house calculation methods and interpretation JSONs
Author-email: Mirjan Ali Sha <mastools.help@gmail.com>
License-Expression: MIT
Classifier: Programming Language :: Python :: 3
Classifier: Operating System :: OS Independent
Classifier: Intended Audience :: Religion
Classifier: Intended Audience :: Education
Classifier: Topic :: Education
Classifier: Topic :: Religion
Classifier: Topic :: Scientific/Engineering :: Astronomy
Requires-Python: >=3.8
License-File: LICENSE
Requires-Dist: pyswisseph>=2.10.3.2
Requires-Dist: matplotlib>=3.0
Dynamic: license-file
